ocean_lib/__init__.py
ocean_lib/example_config.py
ocean_lib/exceptions.py
ocean_lib/agreements/__init__.py
ocean_lib/agreements/consumable.py
ocean_lib/agreements/service_types.py
ocean_lib/aquarius/__init__.py
ocean_lib/aquarius/aquarius.py
ocean_lib/assets/__init__.py
ocean_lib/assets/asset_downloader.py
ocean_lib/assets/credentials.py
ocean_lib/assets/ddo.py
ocean_lib/data_provider/__init__.py
ocean_lib/data_provider/base.py
ocean_lib/data_provider/data_encryptor.py
ocean_lib/data_provider/data_service_provider.py
ocean_lib/data_provider/fileinfo_provider.py
ocean_lib/http_requests/__init__.py
ocean_lib/http_requests/requests_session.py
ocean_lib/models/__init__.py
ocean_lib/models/compute_input.py
ocean_lib/models/data_nft.py
ocean_lib/models/data_nft_factory.py
ocean_lib/models/datatoken1.py
ocean_lib/models/datatoken2.py
ocean_lib/models/datatoken_base.py
ocean_lib/models/dispenser.py
ocean_lib/models/erc721_token_factory_base.py
ocean_lib/models/factory_router.py
ocean_lib/models/fixed_rate_exchange.py
ocean_lib/models/df/df_rewards.py
ocean_lib/models/df/df_strategy_v1.py
ocean_lib/models/ve/smart_wallet_checker.py
ocean_lib/models/ve/ve_allocate.py
ocean_lib/models/ve/ve_delegation.py
ocean_lib/models/ve/ve_fee_distributor.py
ocean_lib/models/ve/ve_fee_estimate.py
ocean_lib/models/ve/ve_ocean.py
ocean_lib/ocean/__init__.py
ocean_lib/ocean/crypto.py
ocean_lib/ocean/mint_fake_ocean.py
ocean_lib/ocean/ocean.py
ocean_lib/ocean/ocean_assets.py
ocean_lib/ocean/ocean_compute.py
ocean_lib/ocean/util.py
ocean_lib/services/consumer_parameters.py
ocean_lib/services/service.py
ocean_lib/structures/abi_tuples.py
ocean_lib/structures/algorithm_metadata.py
ocean_lib/structures/file_objects.py
ocean_lib/web3_internal/__init__.py
ocean_lib/web3_internal/clef.py
ocean_lib/web3_internal/constants.py
ocean_lib/web3_internal/contract_base.py
ocean_lib/web3_internal/contract_utils.py
ocean_lib/web3_internal/http_provider.py
ocean_lib/web3_internal/request.py
ocean_lib-3.1.2.dist-info/LICENSE
ocean_lib-3.1.2.dist-info/METADATA
ocean_lib-3.1.2.dist-info/WHEEL
ocean_lib-3.1.2.dist-info/top_level.txt
ocean_lib-3.1.2.dist-info/RECORD
