Metadata-Version: 2.1
Name: ocean-lib
Version: 3.1.2
Summary: 🐳 Ocean protocol library.
Home-page: https://github.com/oceanprotocol/ocean.py
Author: ocean-core-team
Author-email: devops@oceanprotocol.com
License: Apache Software License 2.0
Keywords: ocean-lib
Classifier: Development Status :: 4 - Beta
Classifier: Intended Audience :: Developers
Classifier: License :: OSI Approved :: Apache Software License
Classifier: Natural Language :: English
Classifier: Programming Language :: Python :: 3.8
License-File: LICENSE
Requires-Dist: ocean-contracts==2.0.3
Requires-Dist: coloredlogs==15.0.1
Requires-Dist: requests>=2.21.0
Requires-Dist: pytz
Requires-Dist: enforce-typing==1.0.0.post1
Requires-Dist: eciespy==0.4.1
Requires-Dist: cryptography==41.0.7
Requires-Dist: web3==6.11.4
Provides-Extra: test
Requires-Dist: codacy-coverage==1.3.11; extra == "test"
Requires-Dist: coverage==7.3.2; extra == "test"
Requires-Dist: mccabe==0.7.0; extra == "test"
Requires-Dist: pytest==7.4.3; extra == "test"
Requires-Dist: pytest-watch==4.2.0; extra == "test"
Requires-Dist: pytest-env; extra == "test"
Requires-Dist: matplotlib; extra == "test"
Requires-Dist: mkcodes==0.1.1; extra == "test"
Requires-Dist: pytest-sugar==0.9.7; extra == "test"
Provides-Extra: dev
Requires-Dist: bumpversion==0.6.0; extra == "dev"
Requires-Dist: pkginfo==1.9.6; extra == "dev"
Requires-Dist: twine==4.0.2; extra == "dev"
Requires-Dist: watchdog==3.0.0; extra == "dev"
Requires-Dist: isort==5.12.0; extra == "dev"
Requires-Dist: flake8==6.1.0; extra == "dev"
Requires-Dist: black; extra == "dev"
Requires-Dist: pre-commit==3.5.0; extra == "dev"
Requires-Dist: licenseheaders==0.8.8; extra == "dev"
Requires-Dist: codacy-coverage==1.3.11; extra == "dev"
Requires-Dist: coverage==7.3.2; extra == "dev"
Requires-Dist: mccabe==0.7.0; extra == "dev"
Requires-Dist: pytest==7.4.3; extra == "dev"
Requires-Dist: pytest-watch==4.2.0; extra == "dev"
Requires-Dist: pytest-env; extra == "dev"
Requires-Dist: matplotlib; extra == "dev"
Requires-Dist: mkcodes==0.1.1; extra == "dev"
Requires-Dist: pytest-sugar==0.9.7; extra == "dev"
